pack_uniprot/__init__.py
pack_uniprot/uniprot.py
pack_uniprot/uniprot_collection.py
pack_uniprot-0.1.2.dist-info/METADATA
pack_uniprot-0.1.2.dist-info/WHEEL
pack_uniprot-0.1.2.dist-info/top_level.txt
pack_uniprot-0.1.2.dist-info/RECORD
