Metadata-Version: 2.1
Name: pack_uniprot
Version: 0.1.2
Summary: Add your description here
Requires-Python: >=3.12
Requires-Dist: matplotlib>=3.9.2
